[{"Atleta": {"atleta_id": 68952, "nome": "Mário Sérgio Santos Costa", "apelido": "Marinho", "foto": "https://s.glbimg.com/es/sde/f/2019/05/30/cd8a7f9b0744e105efa0a0c572d37d6f_FORMATO.png", "preco_editorial": 5}, "escalacoes": 2072549, "clube": "SAN", "clube_nome": "Santos", "clube_id": 277, "escudo_clube": "https://s.glbimg.com/es/sde/f/organizacoes/2014/04/14/santos_60x60.png", "posicao": "Atacante", "posicao_abreviacao": "ATA"}, {"Atleta": {"atleta_id": 87863, "nome": "Giorgian Daniel de Arrascaeta Benedetti", "apelido": "Arrascaeta", "foto": "https://s.glbimg.com/es/sde/f/2020/07/21/6ad752ca6185d76358f944dab95130fd_FORMATO.png", "preco_editorial": 25}, "escalacoes": 2022293, "clube": "FLA", "clube_nome": "Flamengo", "clube_id": 262, "escudo_clube": "https://s.glbimg.com/es/sde/f/organizacoes/2018/04/09/Flamengo-65.png", "posicao": "Meia", "posicao_abreviacao": "MEI"}, {"Atleta": {"atleta_id": 94583, "nome": "Pedro Guilherme Abreu dos Santos", "apelido": "Pedro", "foto": "https://s.glbimg.com/es/sde/f/2020/07/21/be530b20dd27bd402abc125ba7691a18_FORMATO.png", "preco_editorial": 9}, "escalacoes": 1496017, "clube": "FLA", "clube_nome": "Flamengo", "clube_id": 262, "escudo_clube": "https://s.glbimg.com/es/sde/f/organizacoes/2018/04/09/Flamengo-65.png", "posicao": "Atacante", "posicao_abreviacao": "ATA"}, {"Atleta": {"atleta_id": 86485, "nome": "Marcos da Silva França", "apelido": "Keno", "foto": "https://s.glbimg.com/es/sde/f/2020/08/31/1c7eb530ff0944a5fb26c266c76aac9c_FORMATO.png", "preco_editorial": 18}, "escalacoes": 1493357, "clube": "ATL", "clube_nome": "Atlético-MG", "clube_id": 282, "escudo_clube": "https://s.glbimg.com/es/sde/f/organizacoes/2017/11/23/Atletico-Mineiro-escudo65px.png", "posicao": "Atacante", "posicao_abreviacao": "ATA"}, {"Atleta": {"atleta_id": 98974, "nome": "Matías Nicolás Viña Susperreguy", "apelido": "Viña", "foto": "https://s.glbimg.com/es/sde/f/2020/02/28/444cc845fe792b0fdd234c579e4c31de_FORMATO.png", "preco_editorial": 7}, "escalacoes": 1342304, "clube": "PAL", "clube_nome": "Palmeiras", "clube_id": 275, "escudo_clube": "https://s.glbimg.com/es/sde/f/organizacoes/2014/04/14/palmeiras_60x60.png", "posicao": "Lateral", "posicao_abreviacao": "LAT"}, {"Atleta": {"atleta_id": 71844, "nome": "Thiago Galhardo do Nascimento Rocha", "apelido": "Thiago Galhardo", "foto": "https://s.glbimg.com/es/sde/f/2020/02/27/58765e09575aeed485460352a0980dad_FORMATO.png", "preco_editorial": 7}, "escalacoes": 1171833, "clube": "INT", "clube_nome": "Internacional", "clube_id": 285, "escudo_clube": "https://s.glbimg.com/es/sde/f/organizacoes/2016/05/03/inter65.png", "posicao": "Meia", "posicao_abreviacao": "MEI"}, {"Atleta": {"atleta_id": 94509, "nome": "Raphael Cavalcante Veiga", "apelido": "Raphael Veiga", "foto": "https://s.glbimg.com/es/sde/f/2019/01/14/e85d3259b80c8d878e2b07eae90749ee_FORMATO.jpeg", "preco_editorial": 9}, "escalacoes": 1151491, "clube": "PAL", "clube_nome": "Palmeiras", "clube_id": 275, "escudo_clube": "https://s.glbimg.com/es/sde/f/organizacoes/2014/04/14/palmeiras_60x60.png", "posicao": "Meia", "posicao_abreviacao": "MEI"}, {"Atleta": {"atleta_id": 90285, "nome": "Bruno Henrique Pinto", "apelido": "Bruno Henrique", "foto": "https://s.glbimg.com/es/sde/f/2020/07/21/c6deeaacd987fda728f5e5cb9a7d733c_FORMATO.png", "preco_editorial": 20}, "escalacoes": 1133283, "clube": "FLA", "clube_nome": "Flamengo", "clube_id": 262, "escudo_clube": "https://s.glbimg.com/es/sde/f/organizacoes/2018/04/09/Flamengo-65.png", "posicao": "Atacante", "posicao_abreviacao": "ATA"}, {"Atleta": {"atleta_id": 85425, "nome": "João Paulo Silva Martins", "apelido": "João Paulo", "foto": "https://s.glbimg.com/es/sde/f/2019/03/28/55b6bd3285315d25077f61ea5d4a7fc9_FORMATO.png", "preco_editorial": 2}, "escalacoes": 1029179, "clube": "SAN", "clube_nome": "Santos", "clube_id": 277, "escudo_clube": "https://s.glbimg.com/es/sde/f/organizacoes/2014/04/14/santos_60x60.png", "posicao": "Goleiro", "posicao_abreviacao": "GOL"}, {"Atleta": {"atleta_id": 71684, "nome": "Gustavo Raúl Gómez Portillo", "apelido": "Gustavo Gómez", "foto": "https://s.glbimg.com/es/sde/f/2020/03/09/d8945e5024344014b96d64adab91f4da_FORMATO.png", "preco_editorial": 15}, "escalacoes": 955525, "clube": "PAL", "clube_nome": "Palmeiras", "clube_id": 275, "escudo_clube": "https://s.glbimg.com/es/sde/f/organizacoes/2014/04/14/palmeiras_60x60.png", "posicao": "Zagueiro", "posicao_abreviacao": "ZAG"}, {"Atleta": {"atleta_id": 52253, "nome": "Réver Humberto Alves Araújo", "apelido": "Réver", "foto": "https://s.glbimg.com/es/sde/f/2020/08/31/3b64f778984d4cc9daab96fb66d28946_FORMATO.png", "preco_editorial": 9}, "escalacoes": 837317, "clube": "ATL", "clube_nome": "Atlético-MG", "clube_id": 282, "escudo_clube": "https://s.glbimg.com/es/sde/f/organizacoes/2017/11/23/Atletico-Mineiro-escudo65px.png", "posicao": "Zagueiro", "posicao_abreviacao": "ZAG"}, {"Atleta": {"atleta_id": 107172, "nome": "Patrick de Paula Carreiro", "apelido": "Patrick de Paula", "foto": "https://s.glbimg.com/es/sde/f/2020/03/09/a9c14c249329965a83e2f3b2bda2642b_FORMATO.png", "preco_editorial": 3}, "escalacoes": 767244, "clube": "PAL", "clube_nome": "Palmeiras", "clube_id": 275, "escudo_clube": "https://s.glbimg.com/es/sde/f/organizacoes/2014/04/14/palmeiras_60x60.png", "posicao": "Meia", "posicao_abreviacao": "MEI"}, {"Atleta": {"atleta_id": 37281, "nome": "Luis Antônio Venker de Menezes", "apelido": "Mano Menezes", "foto": "https://s.glbimg.com/es/sde/f/2020/09/11/e6334f42f000ffd6983a97fbf4f01ae2_FORMATO.png", "preco_editorial": 8.06}, "escalacoes": 746177, "clube": "BAH", "clube_nome": "Bahia", "clube_id": 265, "escudo_clube": "https://s.glbimg.com/es/sde/f/organizacoes/2014/04/14/bahia_60x60.png", "posicao": "Técnico", "posicao_abreviacao": "TEC"}, {"Atleta": {"atleta_id": 80287, "nome": "Luciano da Rocha Neves", "apelido": "Luciano", "foto": "https://s.glbimg.com/es/sde/f/2020/08/18/3ca611370a41964d7e12a7d04a9474aa_FORMATO.png", "preco_editorial": 6}, "escalacoes": 699815, "clube": "SAO", "clube_nome": "São Paulo", "clube_id": 276, "escudo_clube": "https://s.glbimg.com/es/sde/f/organizacoes/2014/04/14/sao_paulo_60x60.png", "posicao": "Atacante", "posicao_abreviacao": "ATA"}, {"Atleta": {"atleta_id": 107110, "nome": "Natan Bernardo de Souza", "apelido": "Natan", "foto": "https://s.glbimg.com/es/sde/f/2020/09/21/f0d9224327f2b48738ff94bbb145695c_FORMATO.png", "preco_editorial": 1}, "escalacoes": 686277, "clube": "FLA", "clube_nome": "Flamengo", "clube_id": 262, "escudo_clube": "https://s.glbimg.com/es/sde/f/organizacoes/2018/04/09/Flamengo-65.png", "posicao": "Zagueiro", "posicao_abreviacao": "ZAG"}, {"Atleta": {"atleta_id": 38913, "nome": "Anderson Luiz de Carvalho", "apelido": "Nenê", "foto": "https://s.glbimg.com/es/sde/f/2020/08/11/f3df6bdc76524f571ea66cc968ab62af_FORMATO.png", "preco_editorial": 9}, "escalacoes": 658171, "clube": "FLU", "clube_nome": "Fluminense", "clube_id": 266, "escudo_clube": "https://s.glbimg.com/es/sde/f/organizacoes/2014/04/14/fluminense_60x60.png", "posicao": "Meia", "posicao_abreviacao": "MEI"}, {"Atleta": {"atleta_id": 97341, "nome": "Rogério Ceni", "apelido": "Rogério Ceni", "foto": "https://s.glbimg.com/es/sde/f/2019/09/27/75459ae60b5baaac5178846f60fbfbed_FORMATO.png", "preco_editorial": 8}, "escalacoes": 635844, "clube": "FOR", "clube_nome": "Fortaleza", "clube_id": 356, "escudo_clube": "https://s.glbimg.com/es/sde/f/organizacoes/2018/06/10/fortaleza-ec-65px.png", "posicao": "Técnico", "posicao_abreviacao": "TEC"}, {"Atleta": {"atleta_id": 38545, "nome": "Felipe Melo de Carvalho", "apelido": "Felipe Melo", "foto": "https://s.glbimg.com/es/sde/f/2020/03/09/54d3936a3f4591a9d700ba26b7fd9e91_FORMATO.png", "preco_editorial": 8}, "escalacoes": 623410, "clube": "PAL", "clube_nome": "Palmeiras", "clube_id": 275, "escudo_clube": "https://s.glbimg.com/es/sde/f/organizacoes/2014/04/14/palmeiras_60x60.png", "posicao": "Zagueiro", "posicao_abreviacao": "ZAG"}, {"Atleta": {"atleta_id": 84847, "nome": "Luan Peres Petroni", "apelido": "Luan Peres ", "foto": "https://s.glbimg.com/es/sde/f/2019/09/16/6a774b65d32e1e3586030adb069316e3_FORMATO.png", "preco_editorial": 5}, "escalacoes": 577693, "clube": "SAN", "clube_nome": "Santos", "clube_id": 277, "escudo_clube": "https://s.glbimg.com/es/sde/f/organizacoes/2014/04/14/santos_60x60.png", "posicao": "Zagueiro", "posicao_abreviacao": "ZAG"}, {"Atleta": {"atleta_id": 101708, "nome": "Felipe Jonatan Rocha Andrade", "apelido": "Felipe Jonatan", "foto": "https://s.glbimg.com/es/sde/f/2020/03/09/0b840af999aed1a7ec1a7a35dee46abc_FORMATO.png", "preco_editorial": 7}, "escalacoes": 558133, "clube": "SAN", "clube_nome": "Santos", "clube_id": 277, "escudo_clube": "https://s.glbimg.com/es/sde/f/organizacoes/2014/04/14/santos_60x60.png", "posicao": "Lateral", "posicao_abreviacao": "LAT"}]