[{"Atleta": {"atleta_id": 86485, "nome": "Marcos da Silva França", "apelido": "Keno", "foto": "https://s.glbimg.com/es/sde/f/2020/08/31/1c7eb530ff0944a5fb26c266c76aac9c_FORMATO.png", "preco_editorial": 18}, "escalacoes": 1127749, "clube": "ATL", "clube_nome": "Atlético-MG", "clube_id": 282, "escudo_clube": "https://s.glbimg.com/es/sde/f/organizacoes/2017/11/23/Atletico-Mineiro-escudo65px.png", "posicao": "Atacante", "posicao_abreviacao": "ATA"}, {"Atleta": {"atleta_id": 71844, "nome": "Thiago Galhardo do Nascimento Rocha", "apelido": "Thiago Galhardo", "foto": "https://s.glbimg.com/es/sde/f/2020/02/27/58765e09575aeed485460352a0980dad_FORMATO.png", "preco_editorial": 7}, "escalacoes": 813495, "clube": "INT", "clube_nome": "Internacional", "clube_id": 285, "escudo_clube": "https://s.glbimg.com/es/sde/f/organizacoes/2016/05/03/inter65.png", "posicao": "Meia", "posicao_abreviacao": "MEI"}, {"Atleta": {"atleta_id": 91201, "nome": "Eduardo Gabriel Aquino Cossa", "apelido": "Pepê", "foto": "https://s.glbimg.com/es/sde/f/2018/07/31/21dbd08feda4a4caf00ffc5fe75ec14b_FORMATO.png", "preco_editorial": 8}, "escalacoes": 692919, "clube": "GRE", "clube_nome": "Grêmio", "clube_id": 284, "escudo_clube": "https://s.glbimg.com/es/sde/f/organizacoes/2014/04/14/gremio_60x60.png", "posicao": "Atacante", "posicao_abreviacao": "ATA"}, {"Atleta": {"atleta_id": 94583, "nome": "Pedro Guilherme Abreu dos Santos", "apelido": "Pedro", "foto": "https://s.glbimg.com/es/sde/f/2020/07/21/be530b20dd27bd402abc125ba7691a18_FORMATO.png", "preco_editorial": 9}, "escalacoes": 626889, "clube": "FLA", "clube_nome": "Flamengo", "clube_id": 262, "escudo_clube": "https://s.glbimg.com/es/sde/f/organizacoes/2018/04/09/Flamengo-65.png", "posicao": "Atacante", "posicao_abreviacao": "ATA"}, {"Atleta": {"atleta_id": 87228, "nome": "Guilherme Antonio Arana Lopes", "apelido": "Guilherme Arana", "foto": "https://s.glbimg.com/es/sde/f/2020/08/31/cf251bf07d0350a8081b6b0e7bfb7950_FORMATO.png", "preco_editorial": 17}, "escalacoes": 584744, "clube": "ATL", "clube_nome": "Atlético-MG", "clube_id": 282, "escudo_clube": "https://s.glbimg.com/es/sde/f/organizacoes/2017/11/23/Atletico-Mineiro-escudo65px.png", "posicao": "Lateral", "posicao_abreviacao": "LAT"}, {"Atleta": {"atleta_id": 71162, "nome": "Vinícius Goes Barbosa de Souza", "apelido": "Vinícius", "foto": "https://s.glbimg.com/es/sde/f/2020/07/16/66a1394a24c6d86ac402a7ad916cf196_FORMATO.png", "preco_editorial": 7}, "escalacoes": 564193, "clube": "CEA", "clube_nome": "Ceará", "clube_id": 354, "escudo_clube": "https://s.glbimg.com/es/sde/f/organizacoes/2019/10/10/ceara-65x65.png", "posicao": "Meia", "posicao_abreviacao": "MEI"}, {"Atleta": {"atleta_id": 87009, "nome": "Nathan Allan de Souza", "apelido": "Nathan", "foto": "https://s.glbimg.com/es/sde/f/2020/08/31/1c31d45f66d706f1d16d05f1b5da0056_FORMATO.png", "preco_editorial": 7}, "escalacoes": 555483, "clube": "ATL", "clube_nome": "Atlético-MG", "clube_id": 282, "escudo_clube": "https://s.glbimg.com/es/sde/f/organizacoes/2017/11/23/Atletico-Mineiro-escudo65px.png", "posicao": "Meia", "posicao_abreviacao": "MEI"}, {"Atleta": {"atleta_id": 80853, "nome": "Pedro Tonon Geromel", "apelido": "Pedro Geromel", "foto": "https://s.glbimg.com/es/sde/f/2018/05/21/afc76ea4e9c31e2977ea5e9a90c802b3_FORMATO.png", "preco_editorial": 7}, "escalacoes": 487445, "clube": "GRE", "clube_nome": "Grêmio", "clube_id": 284, "escudo_clube": "https://s.glbimg.com/es/sde/f/organizacoes/2014/04/14/gremio_60x60.png", "posicao": "Zagueiro", "posicao_abreviacao": "ZAG"}, {"Atleta": {"atleta_id": 88312, "nome": "Júnior Osmar Ignacio Alonso Mujica", "apelido": "Júnior Alonso", "foto": "https://s.glbimg.com/es/sde/f/2020/07/16/daf987c3f75852892ad5b645ad99faad_FORMATO.png", "preco_editorial": 6}, "escalacoes": 469619, "clube": "ATL", "clube_nome": "Atlético-MG", "clube_id": 282, "escudo_clube": "https://s.glbimg.com/es/sde/f/organizacoes/2017/11/23/Atletico-Mineiro-escudo65px.png", "posicao": "Zagueiro", "posicao_abreviacao": "ZAG"}, {"Atleta": {"atleta_id": 92630, "nome": "Claudio Luiz Rodrigues Parisi Leonel", "apelido": "Claudinho", "foto": "https://s.glbimg.com/es/sde/f/2020/07/28/552853b4ec9d01e9cfe52d7863da96fd_FORMATO.png", "preco_editorial": 7}, "escalacoes": 453274, "clube": "BGT", "clube_nome": "Bragantino", "clube_id": 280, "escudo_clube": "https://s.glbimg.com/es/sde/f/organizacoes/2020/01/01/65.png", "posicao": "Atacante", "posicao_abreviacao": "ATA"}, {"Atleta": {"atleta_id": 70800, "nome": "Jorge Sampaoli", "apelido": "Jorge Sampaoli", "foto": "https://s.glbimg.com/es/sde/f/2020/07/16/1940a0f1f7b292217e8c59a91c1a05cd_FORMATO.png", "preco_editorial": 12}, "escalacoes": 387641, "clube": "ATL", "clube_nome": "Atlético-MG", "clube_id": 282, "escudo_clube": "https://s.glbimg.com/es/sde/f/organizacoes/2017/11/23/Atletico-Mineiro-escudo65px.png", "posicao": "Técnico", "posicao_abreviacao": "TEC"}, {"Atleta": {"atleta_id": 97867, "nome": "Leonardo Rech Ortiz", "apelido": "Léo Ortiz", "foto": "https://s.glbimg.com/es/sde/f/2020/07/28/090452058da707cf73facf6249235bfb_FORMATO.png", "preco_editorial": 5}, "escalacoes": 357006, "clube": "BGT", "clube_nome": "Bragantino", "clube_id": 280, "escudo_clube": "https://s.glbimg.com/es/sde/f/organizacoes/2020/01/01/65.png", "posicao": "Zagueiro", "posicao_abreviacao": "ZAG"}, {"Atleta": {"atleta_id": 38140, "nome": "Fernando Buttenbender Prass", "apelido": "Fernando Prass", "foto": "https://s.glbimg.com/es/sde/f/2020/03/01/71d59c690cc2fcd14acc5c49fbe44148_FORMATO.png", "preco_editorial": 6}, "escalacoes": 342632, "clube": "CEA", "clube_nome": "Ceará", "clube_id": 354, "escudo_clube": "https://s.glbimg.com/es/sde/f/organizacoes/2019/10/10/ceara-65x65.png", "posicao": "Goleiro", "posicao_abreviacao": "GOL"}, {"Atleta": {"atleta_id": 51772, "nome": "Everton Augusto de Barros Ribeiro", "apelido": "Everton Ribeiro", "foto": "https://s.glbimg.com/es/sde/f/2020/07/21/f06a07026bcc6a97595016101b72e608_FORMATO.png", "preco_editorial": 5}, "escalacoes": 334361, "clube": "FLA", "clube_nome": "Flamengo", "clube_id": 262, "escudo_clube": "https://s.glbimg.com/es/sde/f/organizacoes/2018/04/09/Flamengo-65.png", "posicao": "Meia", "posicao_abreviacao": "MEI"}, {"Atleta": {"atleta_id": 82792, "nome": "Maurício Nogueira Barbieri", "apelido": "Maurício Barbieri", "foto": "https://s.glbimg.com/es/sde/f/2020/09/04/e02bb39b647e439b21dc457b3d833853_FORMATO.png", "preco_editorial": 5.94}, "escalacoes": 332346, "clube": "BGT", "clube_nome": "Bragantino", "clube_id": 280, "escudo_clube": "https://s.glbimg.com/es/sde/f/organizacoes/2020/01/01/65.png", "posicao": "Técnico", "posicao_abreviacao": "TEC"}, {"Atleta": {"atleta_id": 84428, "nome": "Fernando Pereira do Nascimento", "apelido": "Fernando Sobral", "foto": "https://s.glbimg.com/es/sde/f/2020/08/31/e0f18a0e8a5144558982a72313a13ef5_FORMATO.png", "preco_editorial": 3}, "escalacoes": 307070, "clube": "CEA", "clube_nome": "Ceará", "clube_id": 354, "escudo_clube": "https://s.glbimg.com/es/sde/f/organizacoes/2019/10/10/ceara-65x65.png", "posicao": "Meia", "posicao_abreviacao": "MEI"}, {"Atleta": {"atleta_id": 98974, "nome": "Matías Nicolás Viña Susperreguy", "apelido": "Viña", "foto": "https://s.glbimg.com/es/sde/f/2020/02/28/444cc845fe792b0fdd234c579e4c31de_FORMATO.png", "preco_editorial": 7}, "escalacoes": 287884, "clube": "PAL", "clube_nome": "Palmeiras", "clube_id": 275, "escudo_clube": "https://s.glbimg.com/es/sde/f/organizacoes/2014/04/14/palmeiras_60x60.png", "posicao": "Lateral", "posicao_abreviacao": "LAT"}, {"Atleta": {"atleta_id": 101319, "nome": "Cláudio Rodrigues Gomes", "apelido": "Guga", "foto": "https://s.glbimg.com/es/sde/f/2020/08/31/ff263cf2e43da8d3c2b3b688ae237c0c_FORMATO.png", "preco_editorial": 7}, "escalacoes": 284671, "clube": "ATL", "clube_nome": "Atlético-MG", "clube_id": 282, "escudo_clube": "https://s.glbimg.com/es/sde/f/organizacoes/2017/11/23/Atletico-Mineiro-escudo65px.png", "posicao": "Lateral", "posicao_abreviacao": "LAT"}, {"Atleta": {"atleta_id": 38913, "nome": "Anderson Luiz de Carvalho", "apelido": "Nenê", "foto": "https://s.glbimg.com/es/sde/f/2020/08/11/f3df6bdc76524f571ea66cc968ab62af_FORMATO.png", "preco_editorial": 9}, "escalacoes": 246895, "clube": "FLU", "clube_nome": "Fluminense", "clube_id": 266, "escudo_clube": "https://s.glbimg.com/es/sde/f/organizacoes/2014/04/14/fluminense_60x60.png", "posicao": "Meia", "posicao_abreviacao": "MEI"}, {"Atleta": {"atleta_id": 98672, "nome": "Jefferson David Savarino Quintero", "apelido": "Savarino", "foto": "https://s.glbimg.com/es/sde/f/2020/08/31/864520e76c9a189815cf05a7f3f9a096_FORMATO.png", "preco_editorial": 5}, "escalacoes": 238688, "clube": "ATL", "clube_nome": "Atlético-MG", "clube_id": 282, "escudo_clube": "https://s.glbimg.com/es/sde/f/organizacoes/2017/11/23/Atletico-Mineiro-escudo65px.png", "posicao": "Atacante", "posicao_abreviacao": "ATA"}]